orangecontrib/__init__.py
orangecontrib/fairness/__init__.py
orangecontrib/fairness/i18n_config.py
orangecontrib/fairness/evaluation/__init__.py
orangecontrib/fairness/evaluation/scoring.py
orangecontrib/fairness/locale/fairness.de.yml
orangecontrib/fairness/locale/fairness.en.yml
orangecontrib/fairness/locale/fairness.zh.yml
orangecontrib/fairness/modeling/__init__.py
orangecontrib/fairness/modeling/adversarial.py
orangecontrib/fairness/modeling/postprocessing.py
orangecontrib/fairness/widgets/__init__.py
orangecontrib/fairness/widgets/owadversarialdebiasing.py
orangecontrib/fairness/widgets/owasfairness.py
orangecontrib/fairness/widgets/owcombinepreprocessors.py
orangecontrib/fairness/widgets/owdatasetbias.py
orangecontrib/fairness/widgets/owequalizedodds.py
orangecontrib/fairness/widgets/owreweighing.py
orangecontrib/fairness/widgets/owweightedlogisticregression.py
orangecontrib/fairness/widgets/utils.py
orangecontrib/fairness/widgets/icons/adversarial_debiasing.svg
orangecontrib/fairness/widgets/icons/as_fairness_data.svg
orangecontrib/fairness/widgets/icons/category.svg
orangecontrib/fairness/widgets/icons/combine_preprocessors.svg
orangecontrib/fairness/widgets/icons/dataset_bias.svg
orangecontrib/fairness/widgets/icons/eq_odds_postprocessing.svg
orangecontrib/fairness/widgets/icons/fairness_category.svg
orangecontrib/fairness/widgets/icons/reweighing.svg
orangecontrib/fairness/widgets/icons/survival_analysis_category.svg
orangecontrib/fairness/widgets/icons/weighted_log_reg.svg
orangecontrib/fairness/widgets/tests/__init__.py
orangecontrib/fairness/widgets/tests/test_owadversarialdebiasing.py
orangecontrib/fairness/widgets/tests/test_owasfairness.py
orangecontrib/fairness/widgets/tests/test_owdatasetbias.py
orangecontrib/fairness/widgets/tests/test_owequalizedodds.py
orangecontrib/fairness/widgets/tests/test_owreweighing.py
orangecontrib/fairness/widgets/tests/utils.py
Blauwal3_Fairness-1.0.1.dist-info/LICENSE
Blauwal3_Fairness-1.0.1.dist-info/METADATA
Blauwal3_Fairness-1.0.1.dist-info/WHEEL
Blauwal3_Fairness-1.0.1.dist-info/entry_points.txt
Blauwal3_Fairness-1.0.1.dist-info/top_level.txt
Blauwal3_Fairness-1.0.1.dist-info/RECORD
